fts/__init__.py
fts/cli.py
fts/config.py
fts/flags.py
fts/manager.py
fts/py.py
fts/utilities.py
fts/app/__init__.py
fts/app/config.py
fts/app/main.py
fts/app/backend/__init__.py
fts/app/backend/chat.py
fts/app/backend/commands.py
fts/app/backend/contacts.py
fts/app/backend/history.py
fts/app/backend/host.py
fts/app/backend/notepad.py
fts/app/backend/transfer.py
fts/app/backend/library/__init__.py
fts/app/backend/library/config.py
fts/app/backend/library/network.py
fts/app/backend/plugins/__init__.py
fts/app/backend/plugins/commands.py
fts/app/backend/plugins/config.py
fts/app/backend/plugins/importer.py
fts/app/backend/plugins/installer.py
fts/app/backend/plugins/utils.py
fts/app/backend/plugins/verifier.py
fts/app/frontend/__init__.py
fts/app/frontend/chat.py
fts/app/frontend/contacts.py
fts/app/frontend/library.py
fts/app/frontend/notepad.py
fts/app/frontend/requests.py
fts/app/frontend/sending.py
fts/app/frontend/transfers.py
fts/app/style/__init__.py
fts/app/style/tcss.py
fts/commands/__init__.py
fts/commands/cache.py
fts/commands/misc.py
fts/commands/sender.py
fts/commands/server.py
fts/core/__init__.py
fts/core/aliases.py
fts/core/detatched.py
fts/core/dosp.py
fts/core/log_cleaner.py
fts/core/logger.py
fts/core/parser.py
fts/core/secure.py
fts_tool-2.3.0.dist-info/licenses/LICENSE
fts_tool-2.3.0.dist-info/METADATA
fts_tool-2.3.0.dist-info/WHEEL
fts_tool-2.3.0.dist-info/entry_points.txt
fts_tool-2.3.0.dist-info/top_level.txt
fts_tool-2.3.0.dist-info/RECORD
