Metadata-Version: 2.4
Name: fts-tool
Version: 2.3.0
Summary: A lightweight CLI tool and TUI application for fast local-network file transfers and communication.
Author-email: Terabase Studios <terabasestudios@gmail.com>
License: MIT License
Project-URL: Homepage, https://github.com/Terabase-Studios/fts
Project-URL: Repository, https://github.com/Terabase-Studios/fts
Project-URL: Issues, https://github.com/Terabase-Studios/fts/issues
Project-URL: Documentation, https://github.com/Terabase-Studios/fts/wiki
Keywords: file transfer,cli,LAN,fts
Classifier: Programming Language :: Python :: 3
Classifier: License :: OSI Approved :: MIT License
Classifier: Topic :: Communications :: File Sharing
Classifier: Topic :: Utilities
Requires-Python: >=3.9
License-File: LICENSE
Requires-Dist: aiofiles>=24.1.0
Requires-Dist: cryptography>=45.0.7
Requires-Dist: psutil>=7.0.0
Requires-Dist: tqdm>=4.67.1
Requires-Dist: filelock>=3.19.1
Requires-Dist: textual>=6.2.1
Requires-Dist: click>=8.3.0
Requires-Dist: pycrdt<0.13,>=0.12.43
Dynamic: license-file
